swarmauri_embedding_tfidf/TfidfEmbedding.py
swarmauri_embedding_tfidf/__init__.py
swarmauri_embedding_tfidf-0.6.1.dist-info/LICENSE
swarmauri_embedding_tfidf-0.6.1.dist-info/METADATA
swarmauri_embedding_tfidf-0.6.1.dist-info/WHEEL
swarmauri_embedding_tfidf-0.6.1.dist-info/entry_points.txt
swarmauri_embedding_tfidf-0.6.1.dist-info/RECORD
